napari_bigfish/__init__.py
napari_bigfish/_sample_data.py
napari_bigfish/_version.py
napari_bigfish/_widget.py
napari_bigfish/array_util.py
napari_bigfish/bigfishapp.py
napari_bigfish/napari.yaml
napari_bigfish/napari_util.py
napari_bigfish/qtutil.py
napari_bigfish/_tests/__init__.py
napari_bigfish/_tests/test_array_util.py
napari_bigfish/_tests/test_bigfishapp.py
napari_bigfish/_tests/test_napari_util.py
napari_bigfish/_tests/test_qtutil.py
napari_bigfish/_tests/test_sample_data.py
napari_bigfish/_tests/test_widget.py
napari_bigfish-0.8.dist-info/licenses/LICENSE
napari_bigfish-0.8.dist-info/METADATA
napari_bigfish-0.8.dist-info/WHEEL
napari_bigfish-0.8.dist-info/entry_points.txt
napari_bigfish-0.8.dist-info/top_level.txt
napari_bigfish-0.8.dist-info/RECORD
