Metadata-Version: 2.4
Name: napari-bigfish
Version: 0.8
Summary: A napari-plugin providing an alternative GUI for Big-FISH. Big-FISH is a python package for the analysis of smFISH images.
Home-page: https://github.com/MontpellierRessourcesImagerie/napari-bigfish
Author: Volker Baecker
Author-email: volker.baecker@mri.cnrs.fr
License: MIT
Project-URL: Bug Tracker, https://github.com/MontpellierRessourcesImagerie/napari-bigfish/issues
Project-URL: Documentation, https://montpellierressourcesimagerie.github.io/napari-bigfish/
Project-URL: Source Code, https://github.com/MontpellierRessourcesImagerie/napari-bigfish
Project-URL: User Support, https://github.com/MontpellierRessourcesImagerie/napari-bigfish/issues
Classifier: Development Status :: 4 - Beta
Classifier: Framework :: napari
Classifier: Intended Audience :: Developers
Classifier: License :: OSI Approved :: MIT License
Classifier: Operating System :: OS Independent
Classifier: Programming Language :: Python
Classifier: Programming Language :: Python :: 3
Classifier: Programming Language :: Python :: 3 :: Only
Classifier: Programming Language :: Python :: 3.8
Classifier: Programming Language :: Python :: 3.9
Classifier: Programming Language :: Python :: 3.10
Classifier: Topic :: Scientific/Engineering :: Image Processing
Requires-Python: >=3.8
License-File: LICENSE
Requires-Dist: numpy
Requires-Dist: magicgui
Requires-Dist: qtpy
Requires-Dist: pyperclip
Requires-Dist: big-fish
Requires-Dist: scikit-image
Provides-Extra: testing
Requires-Dist: tox; extra == "testing"
Requires-Dist: pytest; extra == "testing"
Requires-Dist: pytest-cov; extra == "testing"
Requires-Dist: pytest-qt; extra == "testing"
Requires-Dist: napari; extra == "testing"
Requires-Dist: pyqt5; extra == "testing"
Dynamic: license-file
